colorize/__init__.py
colorize/constants.py
colorize/main.py
colorizelib-1.0.2.dist-info/LICENSE
colorizelib-1.0.2.dist-info/METADATA
colorizelib-1.0.2.dist-info/WHEEL
colorizelib-1.0.2.dist-info/top_level.txt
colorizelib-1.0.2.dist-info/RECORD
