Metadata-Version: 2.1
Name: colorizelib
Version: 1.0.2
Summary: A simple library to colorize your terminal
Home-page: https://github.com/Bielgomes/colorize.py
Author: Bielgomes
Author-email: Bielgomesdasilva@hotmail.com
Project-URL: Bug Tracker, https://github.com/Bielgomes/Colorize.py/issues
Classifier: Programming Language :: Python :: 3
Classifier: License :: OSI Approved :: The Unlicense (Unlicense)
Classifier: Operating System :: OS Independent
Requires-Python: >=3.6
License-File: LICENSE
